haystack_integrations/components/generators/google_ai/__init__.py
haystack_integrations/components/generators/google_ai/gemini.py
haystack_integrations/components/generators/google_ai/chat/gemini.py
google_ai_haystack-5.4.0.post1.dist-info/METADATA
google_ai_haystack-5.4.0.post1.dist-info/WHEEL
google_ai_haystack-5.4.0.post1.dist-info/licenses/LICENSE.txt
google_ai_haystack-5.4.0.post1.dist-info/RECORD
